hackathon_linc/__init__.py
hackathon_linc/account.py
hackathon_linc/auth.py
hackathon_linc/historic_symbols.py
hackathon_linc/ipaddr.py
hackathon_linc/transactions.py
hackathon_linc-0.1.46.dist-info/AUTHORS.rst
hackathon_linc-0.1.46.dist-info/LICENSE
hackathon_linc-0.1.46.dist-info/METADATA
hackathon_linc-0.1.46.dist-info/WHEEL
hackathon_linc-0.1.46.dist-info/entry_points.txt
hackathon_linc-0.1.46.dist-info/top_level.txt
hackathon_linc-0.1.46.dist-info/RECORD
