Metadata-Version: 2.2
Name: hackathon_linc
Version: 0.1.46
Summary: A package needed to participate i's Hackathon
Home-page: https://github.com/AxelTob/LINC-STEM-Hackathon
Author: Yasser Mahfoud, Pontus Green, Axel Tobieson
Author-email: stem@linclund.com
License: MIT license
Keywords: hackathon_linc
Classifier: Development Status :: 2 - Pre-Alpha
Classifier: Intended Audience :: Developers
Classifier: License :: OSI Approved :: MIT License
Classifier: Natural Language :: English
Classifier: Programming Language :: Python :: 3.6
Classifier: Programming Language :: Python :: 3.7
Classifier: Programming Language :: Python :: 3.8
Requires-Python: >=3.5
License-File: LICENSE
License-File: AUTHORS.rst
Requires-Dist: Click>=7.0
Requires-Dist: requests>=2.0.0
Requires-Dist: pandas>=0.25.3
Requires-Dist: numpy>=1.18.0
Dynamic: author
Dynamic: author-email
Dynamic: classifier
Dynamic: description
Dynamic: home-page
Dynamic: keywords
Dynamic: license
Dynamic: requires-dist
Dynamic: requires-python
Dynamic: summary
